pynventory/__init__.py
pynventory/__main__.py
pynventory/hosts.py
pynventory-1.2.2.dist-info/LICENSE
pynventory-1.2.2.dist-info/METADATA
pynventory-1.2.2.dist-info/WHEEL
pynventory-1.2.2.dist-info/entry_points.txt
pynventory-1.2.2.dist-info/top_level.txt
pynventory-1.2.2.dist-info/RECORD
