Metadata-Version: 2.1
Name: pynventory
Version: 1.2.2
Summary: Generate a Dokuwiki friendly inventory table of you Linux Servers
Home-page: https://github.com/kufsa/pynventory
Author: Kuffer Sam
Author-email: sam@skuffer.org
License: MIT
Platform: UNKNOWN
Classifier: License :: OSI Approved :: MIT License
Classifier: Programming Language :: Python
Classifier: Programming Language :: Python :: 3
Requires-Dist: fabric
